markata_slides/__init__.py
markata_slides/__main__.py
markata_slides/cli.py
markata_slides/slides.py
markata_slides-0.3.0.dist-info/METADATA
markata_slides-0.3.0.dist-info/WHEEL
markata_slides-0.3.0.dist-info/entry_points.txt
markata_slides-0.3.0.dist-info/licenses/LICENSE
markata_slides-0.3.0.dist-info/RECORD
