Metadata-Version: 2.1
Name: markata-slides
Version: 0.3.0
Summary: None
Project-URL: Homepage, https://github.com/waylonwalker/Markata Slides
Author: Waylon Walker
License: Copyright (c) 2012-2022 Waylon Walker
License-File: LICENSE
Keywords: None
Classifier: Development Status :: 4 - Beta
Classifier: Environment :: Plugins
Classifier: Intended Audience :: Developers
Classifier: Operating System :: MacOS
Classifier: Operating System :: Microsoft :: Windows
Classifier: Operating System :: POSIX :: Linux
Classifier: Programming Language :: Python :: 3.6
Classifier: Programming Language :: Python :: 3.7
Classifier: Programming Language :: Python :: 3.8
Classifier: Programming Language :: Python :: 3.9
Classifier: Programming Language :: Python :: 3.10
Classifier: Typing :: Typed
Requires-Dist: markata
Requires-Dist: markdown-it-py[plugins]
Requires-Dist: mdit-py-plugins
Provides-Extra: dev
Requires-Dist: black; extra == 'dev'
Requires-Dist: bump2version; extra == 'dev'
Requires-Dist: flake8; extra == 'dev'
Requires-Dist: interrogate; extra == 'dev'
Requires-Dist: isort; extra == 'dev'
Requires-Dist: mypy; extra == 'dev'
Requires-Dist: seed-isort-config; extra == 'dev'
